emp_utl/__init__.py
emp_utl/emp_config/__init__.py
emp_utl/emp_config/utl_config.py
emp_utl/emp_logger/__init__.py
emp_utl/emp_logger/utl_logger.py
emp_utl/emp_mysql/__init__.py
emp_utl/emp_mysql/utl_mysql.py
emp_utl-1.2.0.dist-info/licenses/LICENSE.md
emp_utl-1.2.0.dist-info/METADATA
emp_utl-1.2.0.dist-info/WHEEL
emp_utl-1.2.0.dist-info/top_level.txt
emp_utl-1.2.0.dist-info/RECORD
