Metadata-Version: 2.4
Name: emp_utl
Version: 1.2.0
Summary: Customized modules for reusability in Project Enterprise Management Program (EMP)
Home-page: https://github.com/AbdoCherry/EMP_UTL-S
Author: AbdoCherry
License: MIT
Classifier: Programming Language :: Python :: 3
Classifier: License :: OSI Approved :: MIT License
Classifier: Operating System :: OS Independent
Requires-Python: >=3.8
License-File: LICENSE.md
Requires-Dist: attrs==24.2.0
Requires-Dist: boltons==24.1.0
Requires-Dist: certifi==2024.8.30
Requires-Dist: charset-normalizer==3.4.0
Requires-Dist: config-client==1.4.0
Requires-Dist: confluent-kafka==2.12.0
Requires-Dist: docutils==0.21.2
Requires-Dist: face==24.0.0
Requires-Dist: feather-format==0.4.1
Requires-Dist: glom==24.11.0
Requires-Dist: idna==3.10
Requires-Dist: importlib_metadata==8.5.0
Requires-Dist: jaraco.classes==3.4.0
Requires-Dist: jaraco.context==6.0.1
Requires-Dist: jaraco.functools==4.1.0
Requires-Dist: keyring==25.5.0
Requires-Dist: markdown-it-py==3.0.0
Requires-Dist: mdurl==0.1.2
Requires-Dist: more-itertools==10.5.0
Requires-Dist: mysql-connector-python==9.1.0
Requires-Dist: nh3==0.2.18
Requires-Dist: numpy==2.1.3
Requires-Dist: pandas==2.2.3
Requires-Dist: pkginfo==1.10.0
Requires-Dist: pyarrow==18.0.0
Requires-Dist: Pygments==2.18.0
Requires-Dist: python-dateutil==2.9.0.post0
Requires-Dist: pytz==2024.2
Requires-Dist: readme_renderer==44.0
Requires-Dist: requests==2.32.3
Requires-Dist: requests-toolbelt==1.0.0
Requires-Dist: rfc3986==2.0.0
Requires-Dist: rich==13.9.4
Requires-Dist: ruff==0.11.7
Requires-Dist: setuptools==75.5.0
Requires-Dist: six==1.16.0
Requires-Dist: twine==5.1.1
Requires-Dist: tzdata==2024.2
Requires-Dist: urllib3==2.2.3
Requires-Dist: wheel==0.45.0
Requires-Dist: zipp==3.21.0
Dynamic: author
Dynamic: classifier
Dynamic: description
Dynamic: description-content-type
Dynamic: home-page
Dynamic: license
Dynamic: license-file
Dynamic: requires-dist
Dynamic: requires-python
Dynamic: summary
